{"ratio": [], "shift": [["PRODUCE,PROJECT", 0], ["PRODUCE,JOB", 0], ["MAKE,PROJECT", 0], ["MAKE,SCHOOL", 0], ["IN,IMAGE", 0], ["IN,PROJECT", 0], ["HAD,TAG", 0], ["HAD,PROJECT", 0]], "colors": [["annotation_color", "#b35806"], ["annotation_text_color", "#f7f7f7"], ["association_attribute_text_color", "#000000"], ["association_cartouche_color", "#fdb863"], ["association_cartouche_text_color", "#000000"], ["association_color", "#fee0b6"], ["association_stroke_color", "#e08214"], ["background_color", "#f7f7f7"], ["card_text_color", "#542788"], ["entity_attribute_text_color", "#000000"], ["entity_cartouche_color", "#b2abd2"], ["entity_cartouche_text_color", "#000000"], ["entity_color", "#d8daeb"], ["entity_stroke_color", "#8073ac"], ["leg_stroke_color", "#e08214"], ["transparent_color", "none"]], "cy": [["JOB", 85], ["PRODUCE", 85], ["MAKE", 85], ["SCHOOL", 85], ["IMAGE", 246], ["IN", 246], ["PROJECT", 246], ["HAD", 246], ["TAG", 246], ["ABOUT", 458], ["USER", 458], ["MESSAGE", 458]], "cx": [["JOB", 48], ["PRODUCE", 156], ["MAKE", 264], ["SCHOOL", 370], ["IMAGE", 48], ["IN", 156], ["PROJECT", 264], ["HAD", 370], ["TAG", 460], ["ABOUT", 156], ["USER", 264], ["MESSAGE", 370]], "size": [506, 586]}